lab-1-1-mux/design.vhd
library IEEE;
use IEEE.std_logic_1164.all;

entity Mux16to1 is
port(
  S3: in std_logic;
  S2: in std_logic;
  S1: in std_logic;
  S0: in std_logic;

  D0: in std_logic;
  D1: in std_logic;
  D2: in std_logic;
  D3: in std_logic;
  D4: in std_logic;
  D5: in std_logic;
  D6: in std_logic;
  D7: in std_logic;
  D8: in std_logic;
  D9: in std_logic;
  D10: in std_logic;
  D11: in std_logic;
  D12: in std_logic;
  D13: in std_logic;
  D14: in std_logic;
  D15: in std_logic;
  
  Y: out std_logic);
end Mux16to1 ;

architecture rtl of Mux16to1  is
begin
  Y <= (D0 and not S3 and not S2 and not S1 and not S0) or
       (D1 and not S3 and not S2 and not S1 and S0) or
       (D2 and not S3 and not S2 and S1 and not S0) or
       (D3 and not S3 and not S2 and S1 and S0) or
       (D4 and not S3 and S2 and not S1 and not S0) or
       (D5 and not S3 and S2 and not S1 and S0) or
       (D6 and not S3 and S2 and S1 and not S0) or
       (D7 and not S3 and S2 and S1 and S0) or
       (D8 and S3 and not S2 and not S1 and not S0) or
       (D9 and S3 and not S2 and not S1 and S0) or
       (D10 and S3 and not S2 and S1 and not S0) or
       (D11 and S3 and not S2 and S1 and S0) or
       (D12 and S3 and S2 and not S1 and not S0) or
       (D13 and S3 and S2 and not S1 and S0) or
       (D14 and S3 and S2 and S1 and not S0) or
       (D15 and S3 and S2 and S1 and S0);
end rtl;

lab-1-1-mux/testbench.vhd
-- Testbench for OR gate
library IEEE;
use IEEE.std_logic_1164.all;
 
entity testbench is
-- empty
end testbench; 

architecture tb of testbench is

-- DUT component
component Mux16to1  is
port(
  S3: in std_logic;
  S2: in std_logic;
  S1: in std_logic;
  S0: in std_logic;

  D0: in std_logic;
  D1: in std_logic;
  D2: in std_logic;
  D3: in std_logic;
  D4: in std_logic;
  D5: in std_logic;
  D6: in std_logic;
  D7: in std_logic;
  D8: in std_logic;
  D9: in std_logic;
  D10: in std_logic;
  D11: in std_logic;
  D12: in std_logic;
  D13: in std_logic;
  D14: in std_logic;
  D15: in std_logic;
  Y: out std_logic);
end component;

signal S3_in, S2_in, S1_in, S0_in: std_logic;
signal D0_in, D1_in, D2_in, D3_in, D4_in, D5_in, D6_in, D7_in: std_logic;
signal D8_in, D9_in, D10_in, D11_in, D12_in, D13_in, D14_in, D15_in: std_logic;
signal Y: std_logic;

begin

  -- Connect DUT
  DUT: Mux16to1  port map(
    S3_in, S2_in, S1_in, S0_in,
    D0_in, D1_in, D2_in, D3_in, D4_in, D5_in, D6_in, D7_in,
    D8_in, D9_in, D10_in, D11_in, D12_in, D13_in, D14_in, D15_in,
    Y);

  process
  begin
    -- Initialize all inputs to 0
    D0_in <= '0'; D1_in <= '0'; D2_in <= '0'; D3_in <= '0';
    D4_in <= '0'; D5_in <= '0'; D6_in <= '0'; D7_in <= '0';
    D8_in <= '0'; D9_in <= '0'; D10_in <= '0'; D11_in <= '0';
    D12_in <= '0'; D13_in <= '0'; D14_in <= '0'; D15_in <= '0';

    -- Test D0 (S3=0, S2=0, S1=0, S0=0)
    S3_in <= '0'; S2_in <= '0'; S1_in <= '0'; S0_in <= '0';
    D0_in <= '1';
    wait for 1 ns;
    assert(Y='1') report "Fail: Select D0" severity error;
    D0_in <= '0';

    -- Test D1 (S3=0, S2=0, S1=0, S0=1)
    S3_in <= '0'; S2_in <= '0'; S1_in <= '0'; S0_in <= '1';
    D1_in <= '1';
    wait for 1 ns;
    assert(Y='1') report "Fail: Select D1" severity error;
    D1_in <= '0';

    -- Test D2 (S3=0, S2=0, S1=1, S0=0)
    S3_in <= '0'; S2_in <= '0'; S1_in <= '1'; S0_in <= '0';
    D2_in <= '1';
    wait for 1 ns;
    assert(Y='1') report "Fail: Select D2" severity error;
    D2_in <= '0';

    -- Test D3 (S3=0, S2=0, S1=1, S0=1)
    S3_in <= '0'; S2_in <= '0'; S1_in <= '1'; S0_in <= '1';
    D3_in <= '1';
    wait for 1 ns;
    assert(Y='1') report "Fail: Select D3" severity error;
    D3_in <= '0';

    -- Test D4 (S3=0, S2=1, S1=0, S0=0)
    S3_in <= '0'; S2_in <= '1'; S1_in <= '0'; S0_in <= '0';
    D4_in <= '1';
    wait for 1 ns;
    assert(Y='1') report "Fail: Select D4" severity error;
    D4_in <= '0';

    -- Test D5 (S3=0, S2=1, S1=0, S0=1)
    S3_in <= '0'; S2_in <= '1'; S1_in <= '0'; S0_in <= '1';
    D5_in <= '1';
    wait for 1 ns;
    assert(Y='1') report "Fail: Select D5" severity error;
    D5_in <= '0';

    -- Test D6 (S3=0, S2=1, S1=1, S0=0)
    S3_in <= '0'; S2_in <= '1'; S1_in <= '1'; S0_in <= '0';
    D6_in <= '1';
    wait for 1 ns;
    assert(Y='1') report "Fail: Select D6" severity error;
    D6_in <= '0';

    -- Test D7 (S3=0, S2=1, S1=1, S0=1)
    S3_in <= '0'; S2_in <= '1'; S1_in <= '1'; S0_in <= '1';
    D7_in <= '1';
    wait for 1 ns;
    assert(Y='1') report "Fail: Select D7" severity error;
    D7_in <= '0';

    -- Test D8 (S3=1, S2=0, S1=0, S0=0)
    S3_in <= '1'; S2_in <= '0'; S1_in <= '0'; S0_in <= '0';
    D8_in <= '1';
    wait for 1 ns;
    assert(Y='1') report "Fail: Select D8" severity error;
    D8_in <= '0';

    -- Test D9 (S3=1, S2=0, S1=0, S0=1)
    S3_in <= '1'; S2_in <= '0'; S1_in <= '0'; S0_in <= '1';
    D9_in <= '1';
    wait for 1 ns;
    assert(Y='1') report "Fail: Select D9" severity error;
    D9_in <= '0';

    -- Test D10 (S3=1, S2=0, S1=1, S0=0)
    S3_in <= '1'; S2_in <= '0'; S1_in <= '1'; S0_in <= '0';
    D10_in <= '1';
    wait for 1 ns;
    assert(Y='1') report "Fail: Select D10" severity error;
    D10_in <= '0';

    -- Test D11 (S3=1, S2=0, S1=1, S0=1)
    S3_in <= '1'; S2_in <= '0'; S1_in <= '1'; S0_in <= '1';
    D11_in <= '1';
    wait for 1 ns;
    assert(Y='1') report "Fail: Select D11" severity error;
    D11_in <= '0';

    -- Test D12 (S3=1, S2=1, S1=0, S0=0)
    S3_in <= '1'; S2_in <= '1'; S1_in <= '0'; S0_in <= '0';
    D12_in <= '1';
    wait for 1 ns;
    assert(Y='1') report "Fail: Select D12" severity error;
    D12_in <= '0';

    -- Test D13 (S3=1, S2=1, S1=0, S0=1)
    S3_in <= '1'; S2_in <= '1'; S1_in <= '0'; S0_in <= '1';
    D13_in <= '1';
    wait for 1 ns;
    assert(Y='1') report "Fail: Select D13" severity error;
    D13_in <= '0';

    -- Test D14 (S3=1, S2=1, S1=1, S0=0)
    S3_in <= '1'; S2_in <= '1'; S1_in <= '1'; S0_in <= '0';
    D14_in <= '1';
    wait for 1 ns;
    assert(Y='1') report "Fail: Select D14" severity error;
    D14_in <= '0';

    -- Test D15 (S3=1, S2=1, S1=1, S0=1)
    S3_in <= '1'; S2_in <= '1'; S1_in <= '1'; S0_in <= '1';
    D15_in <= '1';
    wait for 1 ns;
    assert(Y='1') report "Fail: Select D15" severity error;
    D15_in <= '0';

    assert false report "Test done." severity note;
    wait;
  end process;
end tb;

lab-1-1-mux/dump.vcd
$date
  Tue Jul 14 16:16:10 2026
$end
$version
  GHDL v0
$end
$timescale
  1 fs
$end
$scope module standard $end
$upscope $end
$scope module std_logic_1164 $end
$upscope $end
$scope module testbench $end
$var reg 1 ! s3_in $end
$var reg 1 " s2_in $end
$var reg 1 # s1_in $end
$var reg 1 $ s0_in $end
$var reg 1 % d0_in $end
$var reg 1 & d1_in $end
$var reg 1 ' d2_in $end
$var reg 1 ( d3_in $end
$var reg 1 ) d4_in $end
$var reg 1 * d5_in $end
$var reg 1 + d6_in $end
$var reg 1 , d7_in $end
$var reg 1 - d8_in $end
$var reg 1 . d9_in $end
$var reg 1 / d10_in $end
$var reg 1 0 d11_in $end
$var reg 1 1 d12_in $end
$var reg 1 2 d13_in $end
$var reg 1 3 d14_in $end
$var reg 1 4 d15_in $end
$var reg 1 5 y $end
$scope module dut $end
$var reg 1 6 s3 $end
$var reg 1 7 s2 $end
$var reg 1 8 s1 $end
$var reg 1 9 s0 $end
$var reg 1 : d0 $end
$var reg 1 ; d1 $end
$var reg 1 < d2 $end
$var reg 1 = d3 $end
$var reg 1 > d4 $end
$var reg 1 ? d5 $end
$var reg 1 @ d6 $end
$var reg 1 A d7 $end
$var reg 1 B d8 $end
$var reg 1 C d9 $end
$var reg 1 D d10 $end
$var reg 1 E d11 $end
$var reg 1 F d12 $end
$var reg 1 G d13 $end
$var reg 1 H d14 $end
$var reg 1 I d15 $end
$var reg 1 J y $end
$upscope $end
$upscope $end
$enddefinitions $end
#0
0!
0"
0#
0$
1%
0&
0'
0(
0)
0*
0+
0,
0-
0.
0/
00
01
02
03
04
15
06
07
08
09
1:
0;
0<
0=
0>
0?
0@
0A
0B
0C
0D
0E
0F
0G
0H
0I
1J
#1000000
1$
0%
1&
19
0:
1;
#2000000
1#
0$
0&
1'
18
09
0;
1<
#3000000
1$
0'
1(
19
0<
1=
#4000000
1"
0#
0$
0(
1)
17
08
09
0=
1>
#5000000
1$
0)
1*
19
0>
1?
#6000000
1#
0$
0*
1+
18
09
0?
1@
#7000000
1$
0+
1,
19
0@
1A
#8000000
1!
0"
0#
0$
0,
1-
16
07
08
09
0A
1B
#9000000
1$
0-
1.
19
0B
1C
#10000000
1#
0$
0.
1/
18
09
0C
1D
#11000000
1$
0/
10
19
0D
1E
#12000000
1"
0#
0$
00
11
17
08
09
0E
1F
#13000000
1$
01
12
19
0F
1G
#14000000
1#
0$
02
13
18
09
0G
1H
#15000000
1$
03
14
19
0H
1I
#16000000
04
05
0I
0J
