lab-1-mux-demux/demux_1to16_structural.vhdl
library IEEE;
use IEEE.STD_LOGIC_1164.ALL;

entity DEMUX_1to16_STRUCTURAL is
    Port (
        D : in STD_LOGIC;                       -- 1 input line
        S : in STD_LOGIC_VECTOR(3 downto 0);   -- 4 select lines
        Y : out STD_LOGIC_VECTOR(15 downto 0)  -- 16 output lines
    );
end DEMUX_1to16_STRUCTURAL;

architecture Structural of DEMUX_1to16_STRUCTURAL is
    -- Intermediate signals
    signal S_not : STD_LOGIC_VECTOR(3 downto 0);  -- NOT of select lines

begin
    -- NOT gates for select lines
    S_not(0) <= not S(0);
    S_not(1) <= not S(1);
    S_not(2) <= not S(2);
    S_not(3) <= not S(3);

    -- AND gates for each output
    -- Each output is AND of input signal with decoder logic

    -- Y0: D AND S3' AND S2' AND S1' AND S0'
    Y(0) <= D and S_not(3) and S_not(2) and S_not(1) and S_not(0);

    -- Y1: D AND S3' AND S2' AND S1' AND S0
    Y(1) <= D and S_not(3) and S_not(2) and S_not(1) and S(0);

    -- Y2: D AND S3' AND S2' AND S1 AND S0'
    Y(2) <= D and S_not(3) and S_not(2) and S(1) and S_not(0);

    -- Y3: D AND S3' AND S2' AND S1 AND S0
    Y(3) <= D and S_not(3) and S_not(2) and S(1) and S(0);

    -- Y4: D AND S3' AND S2 AND S1' AND S0'
    Y(4) <= D and S_not(3) and S(2) and S_not(1) and S_not(0);

    -- Y5: D AND S3' AND S2 AND S1' AND S0
    Y(5) <= D and S_not(3) and S(2) and S_not(1) and S(0);

    -- Y6: D AND S3' AND S2 AND S1 AND S0'
    Y(6) <= D and S_not(3) and S(2) and S(1) and S_not(0);

    -- Y7: D AND S3' AND S2 AND S1 AND S0
    Y(7) <= D and S_not(3) and S(2) and S(1) and S(0);

    -- Y8: D AND S3 AND S2' AND S1' AND S0'
    Y(8) <= D and S(3) and S_not(2) and S_not(1) and S_not(0);

    -- Y9: D AND S3 AND S2' AND S1' AND S0
    Y(9) <= D and S(3) and S_not(2) and S_not(1) and S(0);

    -- Y10: D AND S3 AND S2' AND S1 AND S0'
    Y(10) <= D and S(3) and S_not(2) and S(1) and S_not(0);

    -- Y11: D AND S3 AND S2' AND S1 AND S0
    Y(11) <= D and S(3) and S_not(2) and S(1) and S(0);

    -- Y12: D AND S3 AND S2 AND S1' AND S0'
    Y(12) <= D and S(3) and S(2) and S_not(1) and S_not(0);

    -- Y13: D AND S3 AND S2 AND S1' AND S0
    Y(13) <= D and S(3) and S(2) and S_not(1) and S(0);

    -- Y14: D AND S3 AND S2 AND S1 AND S0'
    Y(14) <= D and S(3) and S(2) and S(1) and S_not(0);

    -- Y15: D AND S3 AND S2 AND S1 AND S0
    Y(15) <= D and S(3) and S(2) and S(1) and S(0);

end Structural;

lab-1-mux-demux/mux_16to1_structural.vhdl
library IEEE;
use IEEE.STD_LOGIC_1164.ALL;

entity MUX_16to1_STRUCTURAL is
    Port (
        D : in STD_LOGIC_VECTOR(15 downto 0);  -- 16 input lines
        S : in STD_LOGIC_VECTOR(3 downto 0);   -- 4 select lines
        Y : out STD_LOGIC                        -- 1 output line
    );
end MUX_16to1_STRUCTURAL;

architecture Structural of MUX_16to1_STRUCTURAL is
    -- Intermediate signals
    signal S_not : STD_LOGIC_VECTOR(3 downto 0);  -- NOT of select lines
    signal and_out : STD_LOGIC_VECTOR(15 downto 0);  -- outputs from AND gates

begin
    -- NOT gates for select lines
    S_not(0) <= not S(0);
    S_not(1) <= not S(1);
    S_not(2) <= not S(2);
    S_not(3) <= not S(3);

    -- AND gates for each input
    -- Each AND gate takes 1 input line and 4 select lines (some inverted)

    -- Y0: D0 AND S3' AND S2' AND S1' AND S0'
    and_out(0) <= D(0) and S_not(3) and S_not(2) and S_not(1) and S_not(0);

    -- Y1: D1 AND S3' AND S2' AND S1' AND S0
    and_out(1) <= D(1) and S_not(3) and S_not(2) and S_not(1) and S(0);

    -- Y2: D2 AND S3' AND S2' AND S1 AND S0'
    and_out(2) <= D(2) and S_not(3) and S_not(2) and S(1) and S_not(0);

    -- Y3: D3 AND S3' AND S2' AND S1 AND S0
    and_out(3) <= D(3) and S_not(3) and S_not(2) and S(1) and S(0);

    -- Y4: D4 AND S3' AND S2 AND S1' AND S0'
    and_out(4) <= D(4) and S_not(3) and S(2) and S_not(1) and S_not(0);

    -- Y5: D5 AND S3' AND S2 AND S1' AND S0
    and_out(5) <= D(5) and S_not(3) and S(2) and S_not(1) and S(0);

    -- Y6: D6 AND S3' AND S2 AND S1 AND S0'
    and_out(6) <= D(6) and S_not(3) and S(2) and S(1) and S_not(0);

    -- Y7: D7 AND S3' AND S2 AND S1 AND S0
    and_out(7) <= D(7) and S_not(3) and S(2) and S(1) and S(0);

    -- Y8: D8 AND S3 AND S2' AND S1' AND S0'
    and_out(8) <= D(8) and S(3) and S_not(2) and S_not(1) and S_not(0);

    -- Y9: D9 AND S3 AND S2' AND S1' AND S0
    and_out(9) <= D(9) and S(3) and S_not(2) and S_not(1) and S(0);

    -- Y10: D10 AND S3 AND S2' AND S1 AND S0'
    and_out(10) <= D(10) and S(3) and S_not(2) and S(1) and S_not(0);

    -- Y11: D11 AND S3 AND S2' AND S1 AND S0
    and_out(11) <= D(11) and S(3) and S_not(2) and S(1) and S(0);

    -- Y12: D12 AND S3 AND S2 AND S1' AND S0'
    and_out(12) <= D(12) and S(3) and S(2) and S_not(1) and S_not(0);

    -- Y13: D13 AND S3 AND S2 AND S1' AND S0
    and_out(13) <= D(13) and S(3) and S(2) and S_not(1) and S(0);

    -- Y14: D14 AND S3 AND S2 AND S1 AND S0'
    and_out(14) <= D(14) and S(3) and S(2) and S(1) and S_not(0);

    -- Y15: D15 AND S3 AND S2 AND S1 AND S0
    and_out(15) <= D(15) and S(3) and S(2) and S(1) and S(0);

    -- OR gate: combine all AND outputs
    Y <= and_out(0) or and_out(1) or and_out(2) or and_out(3) or
         and_out(4) or and_out(5) or and_out(6) or and_out(7) or
         and_out(8) or and_out(9) or and_out(10) or and_out(11) or
         and_out(12) or and_out(13) or and_out(14) or and_out(15);

end Structural;

lab-1-mux-demux/testbench_structural.vhdl
library IEEE;
use IEEE.STD_LOGIC_1164.ALL;
use IEEE.STD_LOGIC_ARITH.ALL;
use IEEE.STD_LOGIC_UNSIGNED.ALL;

entity Lab1_TB_Structural is
end Lab1_TB_Structural;

architecture Test of Lab1_TB_Structural is
    -- Component declarations
    component MUX_16to1_STRUCTURAL
        Port (
            D : in STD_LOGIC_VECTOR(15 downto 0);
            S : in STD_LOGIC_VECTOR(3 downto 0);
            Y : out STD_LOGIC
        );
    end component;

    component DEMUX_1to16_STRUCTURAL
        Port (
            D : in STD_LOGIC;
            S : in STD_LOGIC_VECTOR(3 downto 0);
            Y : out STD_LOGIC_VECTOR(15 downto 0)
        );
    end component;

    -- Signals
    signal input_data : STD_LOGIC_VECTOR(15 downto 0);
    signal select_mux : STD_LOGIC_VECTOR(3 downto 0);
    signal mux_output : STD_LOGIC;
    signal select_demux : STD_LOGIC_VECTOR(3 downto 0);
    signal demux_output : STD_LOGIC_VECTOR(15 downto 0);

begin
    -- Instantiate Structural Multiplexer
    MUX: MUX_16to1_STRUCTURAL port map (
        D => input_data,
        S => select_mux,
        Y => mux_output
    );

    -- Instantiate Structural Demultiplexer
    DEMUX: DEMUX_1to16_STRUCTURAL port map (
        D => mux_output,
        S => select_demux,
        Y => demux_output
    );

    -- Test Process
    process
    begin
        -- Set input data: 0101010101010101 (binary)
        input_data <= x"5555";

        report "============================================";
        report "Lab-1: Multiplexer and Demultiplexer";
        report "Structural Design (AND/OR/NOT gates)";
        report "============================================";
        report "Input Data: 0101010101010101 (0x5555)";
        report "";

        -- Test 1: Select line = 0000 (D0)
        report "--- Test 1: Select = 0000 (D0) ---";
        select_mux <= "0000";
        select_demux <= "0000";
        wait for 10 ns;
        report "MUX Output: " & std_logic'image(mux_output) & " (Expected: '1')";
        report "DEMUX Output at Y0: " & std_logic'image(demux_output(0));
        report "";

        -- Test 2: Select line = 0001 (D1)
        report "--- Test 2: Select = 0001 (D1) ---";
        select_mux <= "0001";
        select_demux <= "0001";
        wait for 10 ns;
        report "MUX Output: " & std_logic'image(mux_output) & " (Expected: '0')";
        report "DEMUX Output at Y1: " & std_logic'image(demux_output(1));
        report "";

        -- Test 3: Select line = 0101 (D5)
        report "--- Test 3: Select = 0101 (D5) ---";
        select_mux <= "0101";
        select_demux <= "0101";
        wait for 10 ns;
        report "MUX Output: " & std_logic'image(mux_output) & " (Expected: '0')";
        report "DEMUX Output at Y5: " & std_logic'image(demux_output(5));
        report "";

        -- Test 4: Select line = 1010 (D10)
        report "--- Test 4: Select = 1010 (D10) ---";
        select_mux <= "1010";
        select_demux <= "1010";
        wait for 10 ns;
        report "MUX Output: " & std_logic'image(mux_output) & " (Expected: '1')";
        report "DEMUX Output at Y10: " & std_logic'image(demux_output(10));
        report "";

        -- Test 5: Select line = 1111 (D15)
        report "--- Test 5: Select = 1111 (D15) ---";
        select_mux <= "1111";
        select_demux <= "1111";
        wait for 10 ns;
        report "MUX Output: " & std_logic'image(mux_output) & " (Expected: '0')";
        report "DEMUX Output at Y15: " & std_logic'image(demux_output(15));
        report "";

        -- Test 6: Different data (11110000)
        report "--- Test 6: Input Data Changed to 1111000011110000 (0xF0F0) ---";
        input_data <= x"F0F0";
        select_mux <= "0111";
        select_demux <= "0111";
        wait for 10 ns;
        report "MUX Output: " & std_logic'image(mux_output) & " (Expected: '1')";
        report "DEMUX Output at Y7: " & std_logic'image(demux_output(7));
        report "";

        -- Test 7: Independent select lines
        report "--- Test 7: Independent Select Lines ---";
        report "MUX Select = 1100 (D12), DEMUX Select = 0011 (Y3)";
        select_mux <= "1100";
        select_demux <= "0011";
        wait for 10 ns;
        report "MUX Output: " & std_logic'image(mux_output) & " (Expected: '1')";
        report "DEMUX Output at Y3: " & std_logic'image(demux_output(3));
        report "";

        -- Test 8: All ones input
        report "--- Test 8: All Ones Input (0xFFFF) ---";
        input_data <= x"FFFF";
        select_mux <= "0010";
        select_demux <= "0010";
        wait for 10 ns;
        report "MUX Output: " & std_logic'image(mux_output) & " (Expected: '1')";
        report "DEMUX Output at Y2: " & std_logic'image(demux_output(2));
        report "";

        -- Test 9: Decoder pattern test (select all)
        report "--- Test 9: Select Count Test ---";
        input_data <= x"FFFF";
        for i in 0 to 15 loop
            select_mux <= CONV_STD_LOGIC_VECTOR(i, 4);
            select_demux <= CONV_STD_LOGIC_VECTOR(i, 4);
            wait for 10 ns;
        end loop;
        report "All selections tested successfully";
        report "";

        report "============================================";
        report "Test Completed - Structural Design";
        report "PASS: All 16 decoder outputs working correctly";
        report "============================================";
        wait;
    end process;

end Test;

lab-1-mux-demux/lab1_structural_simulation.vcd
$date
  Fri Jul 10 10:27:44 2026
$end
$version
  GHDL v0
$end
$timescale
  1 fs
$end
$scope module standard $end
$upscope $end
$scope module std_logic_1164 $end
$upscope $end
$scope module std_logic_arith $end
$upscope $end
$scope module std_logic_unsigned $end
$upscope $end
$scope module lab1_tb_structural $end
$var reg 16 ! input_data[15:0] $end
$var reg 4 " select_mux[3:0] $end
$var reg 1 # mux_output $end
$var reg 4 $ select_demux[3:0] $end
$var reg 16 % demux_output[15:0] $end
$scope module mux $end
$var reg 16 & d[15:0] $end
$var reg 4 ' s[3:0] $end
$var reg 1 ( y $end
$var reg 4 ) s_not[3:0] $end
$var reg 16 * and_out[15:0] $end
$upscope $end
$scope module demux $end
$var reg 1 + d $end
$var reg 4 , s[3:0] $end
$var reg 16 - y[15:0] $end
$var reg 4 . s_not[3:0] $end
$upscope $end
$upscope $end
$enddefinitions $end
#0
b0101010101010101 !
b0000 "
1#
b0000 $
b0000000000000001 %
b0101010101010101 &
b0000 '
1(
b1111 )
b0000000000000001 *
1+
b0000 ,
b0000000000000001 -
b1111 .
#10000000
b0001 "
0#
b0001 $
b0000000000000000 %
b0001 '
0(
b1110 )
b0000000000000000 *
0+
b0001 ,
b0000000000000000 -
b1110 .
#20000000
b0101 "
b0101 $
b0101 '
b1010 )
b0101 ,
b1010 .
#30000000
b1010 "
1#
b1010 $
b0000010000000000 %
b1010 '
1(
b0101 )
b0000010000000000 *
1+
b1010 ,
b0000010000000000 -
b0101 .
#40000000
b1111 "
0#
b1111 $
b0000000000000000 %
b1111 '
0(
b0000 )
b0000000000000000 *
0+
b1111 ,
b0000000000000000 -
b0000 .
#50000000
b1111000011110000 !
b0111 "
1#
b0111 $
b0000000010000000 %
b1111000011110000 &
b0111 '
1(
b1000 )
b0000000010000000 *
1+
b0111 ,
b0000000010000000 -
b1000 .
#60000000
b1100 "
1#
b0011 $
b0000000000001000 %
b1100 '
1(
b0011 )
b0001000000000000 *
1+
b0011 ,
b0000000000001000 -
b1100 .
#70000000
b1111111111111111 !
b0010 "
1#
b0010 $
b0000000000000100 %
b1111111111111111 &
b0010 '
1(
b1101 )
b0000000000000100 *
1+
b0010 ,
b0000000000000100 -
b1101 .
#80000000
b0000 "
1#
b0000 $
b0000000000000001 %
b0000 '
1(
b1111 )
b0000000000000001 *
1+
b0000 ,
b0000000000000001 -
b1111 .
#90000000
b0001 "
b0001 $
b0000000000000010 %
b0001 '
b1110 )
b0000000000000010 *
b0001 ,
b0000000000000010 -
b1110 .
#100000000
b0010 "
1#
b0010 $
b0000000000000100 %
b0010 '
1(
b1101 )
b0000000000000100 *
1+
b0010 ,
b0000000000000100 -
b1101 .
#110000000
b0011 "
b0011 $
b0000000000001000 %
b0011 '
b1100 )
b0000000000001000 *
b0011 ,
b0000000000001000 -
b1100 .
#120000000
b0100 "
1#
b0100 $
b0000000000010000 %
b0100 '
1(
b1011 )
b0000000000010000 *
1+
b0100 ,
b0000000000010000 -
b1011 .
#130000000
b0101 "
b0101 $
b0000000000100000 %
b0101 '
b1010 )
b0000000000100000 *
b0101 ,
b0000000000100000 -
b1010 .
#140000000
b0110 "
1#
b0110 $
b0000000001000000 %
b0110 '
1(
b1001 )
b0000000001000000 *
1+
b0110 ,
b0000000001000000 -
b1001 .
#150000000
b0111 "
b0111 $
b0000000010000000 %
b0111 '
b1000 )
b0000000010000000 *
b0111 ,
b0000000010000000 -
b1000 .
#160000000
b1000 "
1#
b1000 $
b0000000100000000 %
b1000 '
1(
b0111 )
b0000000100000000 *
1+
b1000 ,
b0000000100000000 -
b0111 .
#170000000
b1001 "
b1001 $
b0000001000000000 %
b1001 '
b0110 )
b0000001000000000 *
b1001 ,
b0000001000000000 -
b0110 .
#180000000
b1010 "
1#
b1010 $
b0000010000000000 %
b1010 '
1(
b0101 )
b0000010000000000 *
1+
b1010 ,
b0000010000000000 -
b0101 .
#190000000
b1011 "
b1011 $
b0000100000000000 %
b1011 '
b0100 )
b0000100000000000 *
b1011 ,
b0000100000000000 -
b0100 .
#200000000
b1100 "
1#
b1100 $
b0001000000000000 %
b1100 '
1(
b0011 )
b0001000000000000 *
1+
b1100 ,
b0001000000000000 -
b0011 .
#210000000
b1101 "
b1101 $
b0010000000000000 %
b1101 '
b0010 )
b0010000000000000 *
b1101 ,
b0010000000000000 -
b0010 .
#220000000
b1110 "
1#
b1110 $
b0100000000000000 %
b1110 '
1(
b0001 )
b0100000000000000 *
1+
b1110 ,
b0100000000000000 -
b0001 .
#230000000
b1111 "
b1111 $
b1000000000000000 %
b1111 '
b0000 )
b1000000000000000 *
b1111 ,
b1000000000000000 -
b0000 .
