lab-1-2-demux/design.vhd
library IEEE;
use IEEE.std_logic_1164.all;

entity and_gate is
port(
  S3: in std_logic;
  S2: in std_logic;
  S1: in std_logic;
  S0: in std_logic;

  In_signal: in std_logic;

  D0: out std_logic;
  D1: out std_logic;
  D2: out std_logic;
  D3: out std_logic;
  D4: out std_logic;
  D5: out std_logic;
  D6: out std_logic;
  D7: out std_logic;
  D8: out std_logic;
  D9: out std_logic;
  D10: out std_logic;
  D11: out std_logic;
  D12: out std_logic;
  D13: out std_logic;
  D14: out std_logic;
  D15: out std_logic);
end and_gate;

architecture rtl of and_gate is
begin
  D0 <= In_signal and not S3 and not S2 and not S1 and not S0;
  D1 <= In_signal and not S3 and not S2 and not S1 and S0;
  D2 <= In_signal and not S3 and not S2 and S1 and not S0;
  D3 <= In_signal and not S3 and not S2 and S1 and S0;
  D4 <= In_signal and not S3 and S2 and not S1 and not S0;
  D5 <= In_signal and not S3 and S2 and not S1 and S0;
  D6 <= In_signal and not S3 and S2 and S1 and not S0;
  D7 <= In_signal and not S3 and S2 and S1 and S0;
  D8 <= In_signal and S3 and not S2 and not S1 and not S0;
  D9 <= In_signal and S3 and not S2 and not S1 and S0;
  D10 <= In_signal and S3 and not S2 and S1 and not S0;
  D11 <= In_signal and S3 and not S2 and S1 and S0;
  D12 <= In_signal and S3 and S2 and not S1 and not S0;
  D13 <= In_signal and S3 and S2 and not S1 and S0;
  D14 <= In_signal and S3 and S2 and S1 and not S0;
  D15 <= In_signal and S3 and S2 and S1 and S0;
end rtl;

lab-1-2-demux/testbench.vhd
-- Testbench for Demux 1-to-16
library IEEE;
use IEEE.std_logic_1164.all;

entity testbench is
-- empty
end testbench;

architecture tb of testbench is

-- DUT component
component and_gate is
port(
  S3: in std_logic;
  S2: in std_logic;
  S1: in std_logic;
  S0: in std_logic;

  In_signal: in std_logic;

  D0: out std_logic;
  D1: out std_logic;
  D2: out std_logic;
  D3: out std_logic;
  D4: out std_logic;
  D5: out std_logic;
  D6: out std_logic;
  D7: out std_logic;
  D8: out std_logic;
  D9: out std_logic;
  D10: out std_logic;
  D11: out std_logic;
  D12: out std_logic;
  D13: out std_logic;
  D14: out std_logic;
  D15: out std_logic);
end component;

-- Signals
signal S3_in, S2_in, S1_in, S0_in: std_logic;
signal In_signal_in: std_logic;
signal D0_out, D1_out, D2_out, D3_out, D4_out, D5_out, D6_out, D7_out: std_logic;
signal D8_out, D9_out, D10_out, D11_out, D12_out, D13_out, D14_out, D15_out: std_logic;

begin

  -- Connect DUT
  DUT: and_gate port map(
    S3_in, S2_in, S1_in, S0_in,
    In_signal_in,
    D0_out, D1_out, D2_out, D3_out, D4_out, D5_out, D6_out, D7_out,
    D8_out, D9_out, D10_out, D11_out, D12_out, D13_out, D14_out, D15_out);

  process
  begin
    In_signal_in <= '1';  -- Set input signal to 1

    -- Test D0 (S3=0, S2=0, S1=0, S0=0)
    S3_in <= '0'; S2_in <= '0'; S1_in <= '0'; S0_in <= '0';
    wait for 1 ns;
    assert(D0_out='1') report "Fail: D0 should be 1" severity error;
    assert(D1_out='0') report "Fail: D1 should be 0" severity error;

    -- Test D1 (S3=0, S2=0, S1=0, S0=1)
    S3_in <= '0'; S2_in <= '0'; S1_in <= '0'; S0_in <= '1';
    wait for 1 ns;
    assert(D1_out='1') report "Fail: D1 should be 1" severity error;
    assert(D0_out='0') report "Fail: D0 should be 0" severity error;

    -- Test D2 (S3=0, S2=0, S1=1, S0=0)
    S3_in <= '0'; S2_in <= '0'; S1_in <= '1'; S0_in <= '0';
    wait for 1 ns;
    assert(D2_out='1') report "Fail: D2 should be 1" severity error;

    -- Test D3 (S3=0, S2=0, S1=1, S0=1)
    S3_in <= '0'; S2_in <= '0'; S1_in <= '1'; S0_in <= '1';
    wait for 1 ns;
    assert(D3_out='1') report "Fail: D3 should be 1" severity error;

    -- Test D4 (S3=0, S2=1, S1=0, S0=0)
    S3_in <= '0'; S2_in <= '1'; S1_in <= '0'; S0_in <= '0';
    wait for 1 ns;
    assert(D4_out='1') report "Fail: D4 should be 1" severity error;

    -- Test D5 (S3=0, S2=1, S1=0, S0=1)
    S3_in <= '0'; S2_in <= '1'; S1_in <= '0'; S0_in <= '1';
    wait for 1 ns;
    assert(D5_out='1') report "Fail: D5 should be 1" severity error;

    -- Test D6 (S3=0, S2=1, S1=1, S0=0)
    S3_in <= '0'; S2_in <= '1'; S1_in <= '1'; S0_in <= '0';
    wait for 1 ns;
    assert(D6_out='1') report "Fail: D6 should be 1" severity error;

    -- Test D7 (S3=0, S2=1, S1=1, S0=1)
    S3_in <= '0'; S2_in <= '1'; S1_in <= '1'; S0_in <= '1';
    wait for 1 ns;
    assert(D7_out='1') report "Fail: D7 should be 1" severity error;

    -- Test D8 (S3=1, S2=0, S1=0, S0=0)
    S3_in <= '1'; S2_in <= '0'; S1_in <= '0'; S0_in <= '0';
    wait for 1 ns;
    assert(D8_out='1') report "Fail: D8 should be 1" severity error;

    -- Test D9 (S3=1, S2=0, S1=0, S0=1)
    S3_in <= '1'; S2_in <= '0'; S1_in <= '0'; S0_in <= '1';
    wait for 1 ns;
    assert(D9_out='1') report "Fail: D9 should be 1" severity error;

    -- Test D10 (S3=1, S2=0, S1=1, S0=0)
    S3_in <= '1'; S2_in <= '0'; S1_in <= '1'; S0_in <= '0';
    wait for 1 ns;
    assert(D10_out='1') report "Fail: D10 should be 1" severity error;

    -- Test D11 (S3=1, S2=0, S1=1, S0=1)
    S3_in <= '1'; S2_in <= '0'; S1_in <= '1'; S0_in <= '1';
    wait for 1 ns;
    assert(D11_out='1') report "Fail: D11 should be 1" severity error;

    -- Test D12 (S3=1, S2=1, S1=0, S0=0)
    S3_in <= '1'; S2_in <= '1'; S1_in <= '0'; S0_in <= '0';
    wait for 1 ns;
    assert(D12_out='1') report "Fail: D12 should be 1" severity error;

    -- Test D13 (S3=1, S2=1, S1=0, S0=1)
    S3_in <= '1'; S2_in <= '1'; S1_in <= '0'; S0_in <= '1';
    wait for 1 ns;
    assert(D13_out='1') report "Fail: D13 should be 1" severity error;

    -- Test D14 (S3=1, S2=1, S1=1, S0=0)
    S3_in <= '1'; S2_in <= '1'; S1_in <= '1'; S0_in <= '0';
    wait for 1 ns;
    assert(D14_out='1') report "Fail: D14 should be 1" severity error;

    -- Test D15 (S3=1, S2=1, S1=1, S0=1)
    S3_in <= '1'; S2_in <= '1'; S1_in <= '1'; S0_in <= '1';
    wait for 1 ns;
    assert(D15_out='1') report "Fail: D15 should be 1" severity error;
    
    S3_in <= '0'; S2_in <= '0'; S1_in <= '0'; S0_in <= '0';
    wait for 1 ns;


    assert false report "Test done." severity note;
    wait;
  end process;
end tb;

lab-1-2-demux/dump.vcd
$date
  Tue Jul 14 12:44:26 2026
$end
$version
  GHDL v0
$end
$timescale
  1 fs
$end
$scope module standard $end
$upscope $end
$scope module std_logic_1164 $end
$upscope $end
$scope module testbench $end
$var reg 1 ! s3_in $end
$var reg 1 " s2_in $end
$var reg 1 # s1_in $end
$var reg 1 $ s0_in $end
$var reg 1 % in_signal_in $end
$var reg 1 & d0_out $end
$var reg 1 ' d1_out $end
$var reg 1 ( d2_out $end
$var reg 1 ) d3_out $end
$var reg 1 * d4_out $end
$var reg 1 + d5_out $end
$var reg 1 , d6_out $end
$var reg 1 - d7_out $end
$var reg 1 . d8_out $end
$var reg 1 / d9_out $end
$var reg 1 0 d10_out $end
$var reg 1 1 d11_out $end
$var reg 1 2 d12_out $end
$var reg 1 3 d13_out $end
$var reg 1 4 d14_out $end
$var reg 1 5 d15_out $end
$scope module dut $end
$var reg 1 6 s3 $end
$var reg 1 7 s2 $end
$var reg 1 8 s1 $end
$var reg 1 9 s0 $end
$var reg 1 : in_signal $end
$var reg 1 ; d0 $end
$var reg 1 < d1 $end
$var reg 1 = d2 $end
$var reg 1 > d3 $end
$var reg 1 ? d4 $end
$var reg 1 @ d5 $end
$var reg 1 A d6 $end
$var reg 1 B d7 $end
$var reg 1 C d8 $end
$var reg 1 D d9 $end
$var reg 1 E d10 $end
$var reg 1 F d11 $end
$var reg 1 G d12 $end
$var reg 1 H d13 $end
$var reg 1 I d14 $end
$var reg 1 J d15 $end
$upscope $end
$upscope $end
$enddefinitions $end
#0
0!
0"
0#
0$
1%
1&
0'
0(
0)
0*
0+
0,
0-
0.
0/
00
01
02
03
04
05
06
07
08
09
1:
1;
0<
0=
0>
0?
0@
0A
0B
0C
0D
0E
0F
0G
0H
0I
0J
#1000000
1$
0&
1'
19
0;
1<
#2000000
1#
0$
0'
1(
18
09
0<
1=
#3000000
1$
0(
1)
19
0=
1>
#4000000
1"
0#
0$
0)
1*
17
08
09
0>
1?
#5000000
1$
0*
1+
19
0?
1@
#6000000
1#
0$
0+
1,
18
09
0@
1A
#7000000
1$
0,
1-
19
0A
1B
#8000000
1!
0"
0#
0$
0-
1.
16
07
08
09
0B
1C
#9000000
1$
0.
1/
19
0C
1D
#10000000
1#
0$
0/
10
18
09
0D
1E
#11000000
1$
00
11
19
0E
1F
#12000000
1"
0#
0$
01
12
17
08
09
0F
1G
#13000000
1$
02
13
19
0G
1H
#14000000
1#
0$
03
14
18
09
0H
1I
#15000000
1$
04
15
19
0I
1J
#16000000
0!
0"
0#
0$
1&
05
06
07
08
09
1;
0J
